.gitignore
.gitmodules
release.sh
setup.cfg
setup.py
package_builder/__init__.py
package_builder/lilaclib_wrapper.py
package_builder/package.py
package_builder/storage.py
package_builder/utils.py
package_builder.egg-info/PKG-INFO
package_builder.egg-info/SOURCES.txt
package_builder.egg-info/dependency_links.txt
package_builder.egg-info/requires.txt
package_builder.egg-info/top_level.txt
package_builder/third_party/lilac/lilaclib.py
package_builder/third_party/lilac/lilac2/__init__.py
package_builder/third_party/lilac/lilac2/api.py
package_builder/third_party/lilac/lilac2/cmd.py
package_builder/third_party/lilac/lilac2/const.py
package_builder/third_party/lilac/lilac2/lilacpy.py
package_builder/third_party/lilac/lilac2/lilacyaml.py
package_builder/third_party/lilac/lilac2/mail.py
package_builder/third_party/lilac/lilac2/nvchecker.py
package_builder/third_party/lilac/lilac2/packages.py
package_builder/third_party/lilac/lilac2/pkgbuild.py
package_builder/third_party/lilac/lilac2/repo.py
package_builder/third_party/lilac/lilac2/tools.py
package_builder/third_party/lilac/lilac2/typing.py
package_builder/third_party/lilac/vendor/archpkg.py
package_builder/third_party/lilac/vendor/github.py
package_builder/third_party/lilac/vendor/htmlutils.py
package_builder/third_party/lilac/vendor/mailutils.py
package_builder/third_party/lilac/vendor/myutils.py
package_builder/third_party/lilac/vendor/nicelogger.py
package_builder/third_party/lilac/vendor/requestsutils.py
package_builder/third_party/lilac/vendor/serializer.py
package_builder/third_party/lilac/vendor/yamlutils.py