Metadata-Version: 1.1
Name: package-builder
Version: 0.1.9
Summary: Yet another Arch Linux package builder
Home-page: https://gitlab.com/yan12125/package-builder
Author: Chih-Hsuan Yen
Author-email: yan12125@gmail.com
License: GPLv3
Platform: UNKNOWN
Classifier: Development Status :: 3 - Alpha
Classifier: License :: OSI Approved :: GNU General Public License v3 (GPLv3)
Classifier: Programming Language :: Python :: 3
Classifier: Programming Language :: Python :: 3 :: Only
